cloudconsolelink/__init__.py
cloudconsolelink/clouds/__init__.py
cloudconsolelink/clouds/aws/__init__.py
cloudconsolelink/clouds/aws/links.py
cloudconsolelink/clouds/azure/__init__.py
cloudconsolelink/clouds/gcp/__init__.py
cloudconsolelink/clouds/gcp/links.py
cloudconsolelink-1.0.6.dist-info/LICENSE
cloudconsolelink-1.0.6.dist-info/METADATA
cloudconsolelink-1.0.6.dist-info/WHEEL
cloudconsolelink-1.0.6.dist-info/top_level.txt
cloudconsolelink-1.0.6.dist-info/RECORD
