Metadata-Version: 2.1
Name: cloudconsolelink
Version: 1.0.6
Summary: Generate console links for cloud resources
Home-page: https://github.com/Cloudanix/cloud-console-links
Maintainer: Cloudanix
Maintainer-email: ganesh@cloudanix.com
License: apache2
Platform: UNKNOWN
Classifier: Programming Language :: Python :: 3
Classifier: Intended Audience :: Developers
Classifier: License :: OSI Approved :: Apache Software License
Classifier: Natural Language :: English
Classifier: Operating System :: OS Independent
